late_bound_arguments/__init__.py
late_bound_arguments-0.1.2.dist-info/LICENSE
late_bound_arguments-0.1.2.dist-info/WHEEL
late_bound_arguments-0.1.2.dist-info/METADATA
late_bound_arguments-0.1.2.dist-info/RECORD
