Metadata-Version: 2.1
Name: late-bound-arguments
Version: 0.1.2
Summary: Allows evaluating default arguments at function-call time
Home-page: https://github.com/ShakyaMajumdar/late_bound_arguments
License: MIT
Author: Shakya Majumdar
Author-email: shakyamajumdar1@gmail.com
Requires-Python: >=3.10,<4.0
Classifier: License :: OSI Approved :: MIT License
Classifier: Programming Language :: Python :: 3
Classifier: Programming Language :: Python :: 3.10
Project-URL: Repository, https://github.com/ShakyaMajumdar/late_bound_arguments
